bopbot
