Metadata-Version: 1.2
Name: bopbot
Version: 0.1.9
Summary: A high-level API for pyppeteer
Home-page: UNKNOWN
Author: Daniel Pareja
Author-email: ParejaDan@gmail.com
License: UNKNOWN
Platform: UNKNOWN
Requires-Python: >3.7
